g9_api_client/__init__.py
g9_api_client/constants.py
g9_api_client/g9.py
g9_api_client-0.0.5.dist-info/licenses/LICENSE
g9_api_client-0.0.5.dist-info/METADATA
g9_api_client-0.0.5.dist-info/WHEEL
g9_api_client-0.0.5.dist-info/top_level.txt
g9_api_client-0.0.5.dist-info/RECORD
