Metadata-Version: 2.4
Name: g9_api_client
Version: 0.0.5
Summary: Python library to retrieve information from "G9" portal
Author-email: Jose Rolo <ze.p.rolo@gmail.com>
License: Apache-2.0
Keywords: api,g9
Classifier: Programming Language :: Python :: 3
Requires-Python: >=3
License-File: LICENSE
Requires-Dist: aiohttp
Dynamic: license-file
Dynamic: requires-python
